contextualproperties/__init__.py
contextualproperties/context_aware.py
contextualproperties/context_cached.py
contextualproperties/context_manager.py
contextualproperties/contextual_property.py
contextualproperties/exceptions.py
contextualproperties/property_aware.py
contexualproperties-0.0.4b9.dist-info/licenses/LICENSE
contexualproperties-0.0.4b9.dist-info/METADATA
contexualproperties-0.0.4b9.dist-info/WHEEL
contexualproperties-0.0.4b9.dist-info/top_level.txt
contexualproperties-0.0.4b9.dist-info/RECORD
