Metadata-Version: 2.4
Name: contexualproperties
Version: 0.0.4b9
Summary: Toolkit for dynamic data modeling
Author-email: Mason Logan <contextualproperties@masonlogan.com>
Maintainer-email: Mason Logan <contextualproperties@masonlogan.com>
License-Expression: MIT
Project-URL: Homepage, https://codeberg.org/malogan/contextual-properties
Project-URL: Repository, https://codeberg.org/malogan/contextual-properties.git
Project-URL: Bug Tracker, https://codeberg.org/malogan/contextual-properties/issues
Keywords: property,data management
Classifier: Development Status :: 3 - Alpha
Classifier: Programming Language :: Python
Requires-Python: >=3.10
License-File: LICENSE
Dynamic: license-file
